<Patch>
    <Operation Class="PatchOperationConditional">
        <success>Always</success>
        <xpath>/Defs/ThingDef[defName="WoodPlankFloor" and not(stuffCategories)]/costList[WoodLog]</xpath>
        <match Class="PatchOperationSequence">
            <operations>
                <li Class="PatchOperationRemove">
                    <xpath>/Defs/ThingDef[defName="WoodPlankFloor"]/costList/WoodLog</xpath>
                </li>
                <li Class="PatchOperationAdd">
                    <xpath>/Defs/ThingDef[defName="WoodPlankFloor"]</xpath>
                    <value>
                        <stuffCategories>
                            <li>Woody</li>
                        </stuffCategories>
                    </value>
                </li>
                <li Class="PatchOperationAdd">
                    <xpath>/Defs/ThingDef[defName="WoodPlankFloor"]</xpath>
                    <value>
                        <costStuffCount>3</costStuffCount>
                    </value>
                </li>
                <li Class="PatchOperationConditional">
                    <success>Always</success>
                    <xpath>/Defs/ThingDef[defName="WoodPlankFloor"]/constructEffect</xpath>
                    <match Class="PatchOperationRemove">
                        <xpath>/Defs/ThingDef[defName="WoodPlankFloor"]/constructEffect</xpath>
                    </match>
                </li>
            </operations>
        </match>
    </Operation>
</Patch>
